demography/__init__.py
demography/admin.py
demography/apps.py
demography/conf.py
demography/pagination.py
demography/urls.py
demography/management/__init__.py
demography/management/commands/__init__.py
demography/management/commands/bake_census.py
demography/management/commands/bootstrap_census.py
demography/management/commands/legacy_census.py
demography/management/commands/bake/__init__.py
demography/management/commands/bake/_arguments.py
demography/management/commands/bake/_attributes.py
demography/management/commands/bake/aggregate/__init__.py
demography/management/commands/bake/aggregate/_nation.py
demography/management/commands/bake/aggregate/_state.py
demography/management/commands/bake/aggregate/_variable.py
demography/management/commands/bake/export/__init__.py
demography/management/commands/bake/export/_aws.py
demography/management/commands/bake/export/_nation.py
demography/management/commands/bake/export/_state.py
demography/management/commands/bootstrap/__init__.py
demography/management/commands/bootstrap/_arguments.py
demography/management/commands/bootstrap/_attributes.py
demography/management/commands/bootstrap/fetch/__init__.py
demography/management/commands/bootstrap/fetch/_county.py
demography/management/commands/bootstrap/fetch/_district.py
demography/management/commands/bootstrap/fetch/_series.py
demography/management/commands/bootstrap/fetch/_state.py
demography/management/commands/bootstrap/write/__init__.py
demography/management/commands/bootstrap/write/_county.py
demography/management/commands/bootstrap/write/_district.py
demography/management/commands/bootstrap/write/_state.py
demography/migrations/0001_initial.py
demography/migrations/__init__.py
demography/models/__init__.py
demography/models/census_estimate.py
demography/models/census_label.py
demography/models/census_table.py
demography/models/census_variable.py
demography/serializers/__init__.py
demography/serializers/census_estimate.py
politico_civic_demography-0.1.2.dist-info/METADATA
politico_civic_demography-0.1.2.dist-info/RECORD
politico_civic_demography-0.1.2.dist-info/WHEEL
politico_civic_demography-0.1.2.dist-info/top_level.txt
